{
  "山手線": {
    "prefix": "JY",
    "東京": "01", "神田": "02", "秋葉原": "03", "御徒町": "04", "上野": "05",
    "鶯谷": "06", "日暮里": "07", "西日暮里": "08", "田端": "09", "駒込": "10",
    "巣鴨": "11", "大塚": "12", "池袋": "13", "目白": "14", "高田馬場": "15",
    "新大久保": "16", "新宿": "17", "代々木": "18", "原宿": "19", "渋谷": "20",
    "恵比寿": "21", "目黒": "22", "五反田": "23", "大崎": "24", "品川": "25",
    "高輪ゲートウェイ": "26", "田町": "27", "浜松町": "28", "新橋": "29", "有楽町": "30"
  },
  "中央線": {
    "prefix": "JC",
    "東京": "01", "神田": "02", "御茶ノ水": "03", "四ツ谷": "04", "新宿": "05",
    "中野": "06", "高円寺": "07", "阿佐ヶ谷": "08", "荻窪": "09", "西荻窪": "10",
    "吉祥寺": "11", "三鷹": "12", "武蔵境": "13", "東小金井": "14", "武蔵小金井": "15",
    "国分寺": "16", "西国分寺": "17", "国立": "18", "立川": "19", "日野": "20",
    "豊田": "21", "八王子": "22", "西八王子": "23", "高尾": "24"
  },
  "京浜東北線": {
    "prefix": "JK",
    "大宮": "47", "さいたま新都心": "46", "与野": "45", "北浦和": "44", "浦和": "43",
    "南浦和": "42", "蕨": "41", "西川口": "40", "川口": "39", "赤羽": "38",
    "東十条": "37", "王子": "36", "上中里": "35", "田端": "34", "西日暮里": "33",
    "日暮里": "32", "鶯谷": "31", "上野": "30", "御徒町": "29", "秋葉原": "28",
    "神田": "27", "東京": "26", "有楽町": "25", "新橋": "24", "浜松町": "23",
    "田町": "22", "高輪ゲートウェイ": "21", "品川": "20", "大井町": "19", "大森": "18",
    "蒲田": "17", "川崎": "16", "鶴見": "15", "新子安": "14", "東神奈川": "13",
    "横浜": "12"
  },
  "総武線": {
    "prefix": "JB",
    "三鷹": "01", "吉祥寺": "02", "西荻窪": "03", "荻窪": "04", "阿佐ヶ谷": "05",
    "高円寺": "06", "中野": "07", "東中野": "08", "大久保": "09", "新宿": "10",
    "代々木": "11", "千駄ヶ谷": "12", "信濃町": "13", "四ツ谷": "14", "市ヶ谷": "15",
    "飯田橋": "16", "水道橋": "17", "御茶ノ水": "18", "秋葉原": "19", "浅草橋": "20",
    "両国": "21", "錦糸町": "22", "亀戸": "23", "平井": "24", "新小岩": "25",
    "小岩": "26", "市川": "27", "本八幡": "28", "下総中山": "29", "西船橋": "30",
    "船橋": "31", "東船橋": "32", "津田沼": "33", "幕張本郷": "34", "幕張": "35",
    "新検見川": "36", "稲毛": "37", "西千葉": "38", "千葉": "39"
  },
  "埼京線": {
    "prefix": "JA",
    "大崎": "08", "恵比寿": "09", "渋谷": "10", "新宿": "11", "池袋": "12",
    "板橋": "13", "十条": "14", "赤羽": "15", "北赤羽": "16", "浮間舟渡": "17",
    "戸田公園": "18", "戸田": "19", "北戸田": "20", "武蔵浦和": "21", "中浦和": "22",
    "南与野": "23", "与野本町": "24", "北与野": "25", "大宮": "26"
  },
  "湘南新宿ライン": {
    "prefix": "JS",
    "大宮": "24", "浦和": "23", "赤羽": "22", "池袋": "21", "新宿": "20",
    "渋谷": "19", "恵比寿": "18", "大崎": "17", "西大井": "16", "武蔵小杉": "15",
    "横浜": "13"
  },
  "上野東京ライン": {
    "prefix": "JU",
    "上野": "02", "東京": "01"
  },
  "常磐線": {
    "prefix": "JJ",
    "品川": "01", "新橋": "02", "東京": "03", "上野": "04", "日暮里": "05",
    "三河島": "06", "南千住": "07", "北千住": "08", "松戸": "09", "柏": "10"
  },
  "京葉線": {
    "prefix": "JE",
    "東京": "01", "八丁堀": "02", "越中島": "03", "潮見": "04", "新木場": "05",
    "葛西臨海公園": "06", "舞浜": "07", "新浦安": "08", "市川塩浜": "09", "西船橋": "10"
  },
  "横須賀線": {
    "prefix": "JO",
    "東京": "19", "新橋": "18", "品川": "17", "西大井": "16", "武蔵小杉": "15",
    "横浜": "13", "鎌倉": "07"
  },
  "1号線銀座線": {
    "prefix": "G",
    "渋谷": "01", "表参道": "02", "外苑前": "03", "青山一丁目": "04", "赤坂見附": "05",
    "溜池山王": "06", "虎ノ門": "07", "新橋": "08", "銀座": "09", "京橋": "10",
    "日本橋": "11", "三越前": "12", "神田": "13", "末広町": "14", "上野広小路": "15",
    "上野": "16", "稲荷町": "17", "田原町": "18", "浅草": "19"
  },
  "4号線丸ノ内線": {
    "prefix": "M",
    "荻窪": "01", "南阿佐ヶ谷": "02", "新高円寺": "03", "東高円寺": "04",
    "新中野": "05", "中野坂上": "06", "西新宿": "07", "新宿": "08", "新宿三丁目": "09",
    "新宿御苑前": "10", "四谷三丁目": "11", "四ツ谷": "12", "赤坂見附": "13",
    "国会議事堂前": "14", "霞ヶ関": "15", "銀座": "16", "東京": "17", "大手町": "18",
    "淡路町": "19", "御茶ノ水": "20", "本郷三丁目": "21", "後楽園": "22",
    "茗荷谷": "23", "新大塚": "24", "池袋": "25"
  },
  "2号線日比谷線": {
    "prefix": "H",
    "中目黒": "01", "恵比寿": "02", "広尾": "03", "六本木": "04", "神谷町": "05",
    "虎ノ門ヒルズ": "06", "霞ヶ関": "07", "日比谷": "08", "銀座": "09", "東銀座": "10",
    "築地": "11", "八丁堀": "12", "茅場町": "13", "人形町": "14", "小伝馬町": "15",
    "秋葉原": "16", "仲御徒町": "17", "上野": "18", "入谷": "19", "三ノ輪": "20",
    "南千住": "21", "北千住": "22"
  },
  "5号線東西線": {
    "prefix": "T",
    "中野": "01", "落合": "02", "高田馬場": "03", "早稲田": "04", "神楽坂": "05",
    "飯田橋": "06", "九段下": "07", "竹橋": "08", "大手町": "09", "日本橋": "10",
    "茅場町": "11", "門前仲町": "12", "木場": "13", "東陽町": "14", "南砂町": "15",
    "西葛西": "16", "葛西": "17", "浦安": "18", "南行徳": "19", "行徳": "20",
    "妙典": "21", "原木中山": "22", "西船橋": "23"
  },
  "9号線千代田線": {
    "prefix": "C",
    "代々木上原": "01", "代々木公園": "02", "明治神宮前": "03", "表参道": "04",
    "乃木坂": "05", "赤坂": "06", "国会議事堂前": "07", "霞ヶ関": "08",
    "日比谷": "09", "二重橋前": "10", "大手町": "11", "新御茶ノ水": "12",
    "湯島": "13", "根津": "14", "千駄木": "15", "西日暮里": "16",
    "町屋": "17", "北千住": "18", "綾瀬": "19", "北綾瀬": "20"
  },
  "8号線有楽町線": {
    "prefix": "Y",
    "和光市": "01", "地下鉄成増": "02", "地下鉄赤塚": "03", "平和台": "04",
    "氷川台": "05", "小竹向原": "06", "千川": "07", "要町": "08", "池袋": "09",
    "東池袋": "10", "護国寺": "11", "江戸川橋": "12", "飯田橋": "13",
    "市ヶ谷": "14", "麹町": "15", "永田町": "16", "桜田門": "17",
    "有楽町": "18", "銀座一丁目": "19", "新富町": "20", "月島": "21",
    "豊洲": "22", "辰巳": "23", "新木場": "24"
  },
  "11号線半蔵門線": {
    "prefix": "Z",
    "渋谷": "01", "表参道": "02", "青山一丁目": "03", "永田町": "04",
    "半蔵門": "05", "九段下": "06", "神保町": "07", "大手町": "08",
    "三越前": "09", "水天宮前": "10", "清澄白河": "11", "住吉": "12",
    "錦糸町": "13", "押上": "14"
  },
  "7号線南北線": {
    "prefix": "N",
    "目黒": "01", "白金台": "02", "白金高輪": "03", "麻布十番": "04",
    "六本木一丁目": "05", "溜池山王": "06", "永田町": "07", "四ツ谷": "08",
    "市ヶ谷": "09", "飯田橋": "10", "後楽園": "11", "東大前": "12",
    "本駒込": "13", "駒込": "14", "西ヶ原": "15", "王子": "16",
    "王子神谷": "17", "志茂": "18", "赤羽岩淵": "19"
  },
  "13号線副都心線": {
    "prefix": "F",
    "和光市": "01", "地下鉄成増": "02", "地下鉄赤塚": "03", "平和台": "04",
    "氷川台": "05", "小竹向原": "06", "千川": "07", "要町": "08", "池袋": "09",
    "雑司が谷": "10", "西早稲田": "11", "東新宿": "12", "新宿三丁目": "13",
    "北参道": "14", "明治神宮前": "15", "渋谷": "16"
  },
  "浅草線": {
    "prefix": "A",
    "西馬込": "01", "馬込": "02", "中延": "03", "戸越": "04", "五反田": "05",
    "高輪台": "06", "泉岳寺": "07", "三田": "08", "大門": "09", "新橋": "10",
    "東銀座": "11", "宝町": "12", "日本橋": "13", "人形町": "14", "東日本橋": "15",
    "浅草橋": "16", "蔵前": "17", "浅草": "18", "本所吾妻橋": "19", "押上": "20"
  },
  "三田線": {
    "prefix": "I",
    "目黒": "01", "白金台": "02", "白金高輪": "03", "三田": "04", "芝公園": "05",
    "御成門": "06", "内幸町": "07", "日比谷": "08", "大手町": "09", "神保町": "10",
    "水道橋": "11", "春日": "12", "白山": "13", "千石": "14", "巣鴨": "15",
    "西巣鴨": "16", "新板橋": "17", "板橋区役所前": "18", "板橋本町": "19",
    "本蓮沼": "20", "志村坂上": "21", "志村三丁目": "22", "蓮根": "23",
    "西台": "24", "高島平": "25", "新高島平": "26", "西高島平": "27"
  },
  "10号線新宿線": {
    "prefix": "S",
    "新宿": "01", "新宿三丁目": "02", "曙橋": "03", "市ヶ谷": "04",
    "九段下": "05", "神保町": "06", "小川町": "07", "岩本町": "08",
    "馬喰横山": "09", "浜町": "10", "森下": "11", "菊川": "12",
    "住吉": "13", "西大島": "14", "大島": "15", "東大島": "16",
    "船堀": "17", "一之江": "18", "瑞江": "19", "篠崎": "20", "本八幡": "21"
  },
  "12号線大江戸線": {
    "prefix": "E",
    "都庁前": "28", "新宿西口": "01", "東新宿": "02", "若松河田": "03",
    "牛込柳町": "04", "牛込神楽坂": "05", "飯田橋": "06", "春日": "07",
    "本郷三丁目": "08", "上野御徒町": "09", "新御徒町": "10", "蔵前": "11",
    "両国": "12", "森下": "13", "清澄白河": "14", "門前仲町": "15",
    "月島": "16", "勝どき": "17", "築地市場": "18", "汐留": "19",
    "大門": "20", "赤羽橋": "21", "麻布十番": "22", "六本木": "23",
    "青山一丁目": "24", "国立競技場": "25", "代々木": "26", "新宿": "27",
    "西新宿五丁目": "29", "中野坂上": "30", "東中野": "31", "中井": "32",
    "落合南長崎": "33", "新江古田": "34", "練馬": "35", "豊島園": "36",
    "練馬春日町": "37", "光が丘": "38"
  },
  "りんかい線": {
    "prefix": "R",
    "新木場": "01", "東雲": "02", "国際展示場": "03", "東京テレポート": "04",
    "天王洲アイル": "05", "品川シーサイド": "06", "大井町": "07", "大崎": "08"
  },
  "ゆりかもめ": {
    "prefix": "U",
    "新橋": "01", "竹芝": "02", "日の出": "03", "芝浦ふ頭": "04",
    "お台場海浜公園": "05", "東京国際クルーズターミナル": "06", "テレコムセンター": "07",
    "青海": "08", "東京ビッグサイト": "09", "有明": "10", "有明テニスの森": "11",
    "市場前": "12", "豊洲": "13"
  }
}
